party_parrot/__init__.py
party_parrot/__main__.py
party_parrot/party.py
party_parrot/frames/0.txt
party_parrot/frames/1.txt
party_parrot/frames/2.txt
party_parrot/frames/3.txt
party_parrot/frames/4.txt
party_parrot/frames/5.txt
party_parrot/frames/6.txt
party_parrot/frames/7.txt
party_parrot/frames/8.txt
party_parrot/frames/9.txt
party_parrot-0.0.3.data/scripts/main.py
party_parrot-0.0.3.dist-info/METADATA
party_parrot-0.0.3.dist-info/RECORD
party_parrot-0.0.3.dist-info/WHEEL
party_parrot-0.0.3.dist-info/entry_points.txt
party_parrot-0.0.3.dist-info/top_level.txt
