Metadata-Version: 2.1
Name: party-parrot
Version: 0.0.3
Summary: Party or die
Home-page: https://github.com/santiagobasulto/party-parrot
Author: Santiago Basulto
Author-email: santiago.basulto@gmail.com
License: UNKNOWN
Platform: UNKNOWN
Classifier: Programming Language :: Python :: 3
Classifier: License :: OSI Approved :: MIT License
Classifier: Operating System :: OS Independent
Requires-Dist: asciimatics (==1.9.0)
